{
    "default": {},
    "dark": {
        "style": {
            "chart": {
                "backgroundColor": "#1A1A1A",
                "color": "#CCCCCC",
                "layout": {
                    "gutter": {
                        "color": "#4A4A4A"
                    },
                    "labels": {
                        "color": "#CCCCCC"
                    }
                },
                "legend": {
                    "backgroundColor": "#1A1A1A",
                    "color": "#CCCCCC"
                },
                "title": {
                    "color": "#CCCCCC",
                    "subtitle": {
                        "color": "#757575"
                    }
                },
                "tooltip": {
                    "backgroundColor": "#1A1A1A",
                    "backgroundOpacity": 70,
                    "color": "#CCCCCC",
                    "borderColor": "#5A5A5A"
                }
            }
        },
        "table": {
            "th": {
                "backgroundColor": "#1A1A1A",
                "color": "#CCCCCC"
            },
            "td": {
                "backgroundColor": "#1A1A1A",
                "color": "#CCCCCC"
            }
        }
    },
    "celebration": {
        "style": {
            "chart": {
                "backgroundColor": "#FFF8E1",
                "color": "#424242",
                "useGradient": false,
                "layout": {
                    "gutter": {
                        "color": "#5D403730"
                    },
                    "labels": {
                        "color": "#424242"
                    }
                },
                "legend": {
                    "backgroundColor": "#FFF8E1",
                    "color": "#424242"
                },
                "title": {
                    "color": "#424242",
                    "subtitle": {
                        "color": "#757575"
                    }
                },
                "tooltip": {
                    "backgroundColor": "#FFECB3",
                    "backgroundOpacity": 30,
                    "color": "#424242",
                    "borderColor": "#FF8A65"
                }
            }
        },
        "table": {
            "th": {
                "backgroundColor": "#FFF8E1",
                "color": "#424242"
            },
            "td": {
                "backgroundColor": "#FFF8E1",
                "color": "#424242"
            }
        }
    },
    "celebrationNight": {
        "style": {
            "chart": {
                "backgroundColor": "#1E1E1E",
                "color": "#BDBDBD",
                "useGradient": false,
                "layout": {
                    "gutter": {
                        "color": "#5D403730"
                    },
                    "labels": {
                        "color": "#BDBDBD"
                    }
                },
                "legend": {
                    "backgroundColor": "#1E1E1E",
                    "color": "#BDBDBD"
                },
                "title": {
                    "color": "#FFF8E1",
                    "subtitle": {
                        "color": "#BDBDBD"
                    }
                },
                "tooltip": {
                    "backgroundColor": "#1E1E1E",
                    "backgroundOpacity": 30,
                    "color": "#FFF8E1",
                    "borderColor": "#FF8A65"
                }
            }
        },
        "table": {
            "th": {
                "backgroundColor": "#1E1E1E",
                "color": "#BDBDBD"
            },
            "td": {
                "backgroundColor": "#1E1E1E",
                "color": "#BDBDBD"
            }
        }
    },
    "hack": {
        "style": {
            "chart": {
                "backgroundColor": "#1A1A1A",
                "useGradient": false,
                "color": "#99AA99",
                "layout": {
                    "gutter": {
                        "color": "#2A2A2A"
                    },
                    "labels": {
                        "color": "#99CC99"
                    }
                },
                "legend": {
                    "backgroundColor": "#1A1A1A",
                    "color": "#99AA99"
                },
                "title": {
                    "color": "#66CC66",
                    "subtitle": {
                        "color": "#99AA99"
                    }
                },
                "tooltip": {
                    "backgroundColor": "#2A2F2A",
                    "color": "#AACCAA",
                    "borderColor": "#66CC66"
                }
            }
        },
        "table": {
            "th": {
                "backgroundColor": "#1A1A1A",
                "color": "#99AA99"
            },
            "td": {
                "backgroundColor": "#1A1A1A",
                "color": "#AACCAA"
            }
        }
    },
    "zen": {
        "style": {
            "chart": {
                "useGradient": false,
                "backgroundColor": "#fbfafa",
                "color": "#8A9892",
                "layout": {
                    "gutter": {
                        "color": "#F7EDE2"
                    },
                    "labels": {
                        "color": "#A0AC94"
                    }
                },
                "legend": {
                    "backgroundColor": "#fbfafa",
                    "color": "#99AA99"
                },
                "title": {
                    "color": "#8A9892",
                    "subtitle": {
                        "color": "#99AA99"
                    }
                },
                "tooltip": {
                    "backgroundColor": "#fbfafa",
                    "color": "#8A9892"
                }
            }
        },
        "table": {
            "th": {
                "backgroundColor": "#fbfafa",
                "color": "#8F837A"
            },
            "td": {
                "backgroundColor": "#fbfafa",
                "color": "#8F837A"
            }
        }
    },
    "concrete": {
        "style": {
            "chart": {
                "useGradient": false,
                "backgroundColor": "#f6f6fb",
                "color": "#50606C",
                "layout": {
                    "gutter": {
                        "color": "#DDDDDB"
                    },
                    "labels": {
                        "color": "#61747E"
                    }
                },
                "legend": {
                    "backgroundColor": "#f6f6fb",
                    "color": "#61747E"
                },
                "title": {
                    "color": "#50606C",
                    "subtitle": {
                        "color": "#718890"
                    }
                },
                "tooltip": {
                    "backgroundColor": "#f6f6fb",
                    "color": "#50606C"
                }
            }
        },
        "table": {
            "th": {
                "backgroundColor": "#f6f6fb",
                "color": "#50606C"
            },
            "td": {
                "backgroundColor": "#f6f6fb",
                "color": "#50606C"
            }
        }
    }
}